tipping-0.2.1.dist-info/METADATA
tipping-0.2.1.dist-info/WHEEL
tipping-0.2.1.dist-info/licenses/LICENSE
tipping/__init__.py
tipping/_lib_tipping.cpython-311-i386-linux-gnu.so
tipping-0.2.1.dist-info/RECORD
