Metadata-Version: 2.4
Name: tipping
Version: 0.2.1
Classifier: Programming Language :: Rust
Classifier: Programming Language :: Python :: Implementation :: CPython
Classifier: Programming Language :: Python :: Implementation :: PyPy
Requires-Dist: pytest ; extra == 'tests'
Provides-Extra: tests
License-File: LICENSE
Summary: A python binding for the Rust implementation of Tipping algorithm (tipping-rs)
Requires-Python: >=3.8
